gitgeo/__init__.py
gitgeo/country_codes.csv
gitgeo/custom_csv.py
gitgeo/geographies_list.py
gitgeo/geolocation.py
gitgeo/github.py
gitgeo/main.py
gitgeo/mapping.py
gitgeo/multi_repo_scan.py
gitgeo/printers.py
gitgeo/pypi.py
gitgeo/world.json
gitgeo/world_cities.csv
gitgeo-1.0.2.dist-info/LICENSE
gitgeo-1.0.2.dist-info/METADATA
gitgeo-1.0.2.dist-info/WHEEL
gitgeo-1.0.2.dist-info/entry_points.txt
gitgeo-1.0.2.dist-info/top_level.txt
gitgeo-1.0.2.dist-info/RECORD
