Metadata-Version: 2.1
Name: gitgeo
Version: 1.0.2
Summary: Discover the geography of open-source software. Explore the geographic locations of software developers associated with a GitHub repository or a Python (PyPI) package.
Home-page: https://github.com/IQTLabs/GitGeo
Author: John Speed Meyers
Author-email: 54914994+jspeed-meyers@users.noreply.github.com
License: Apache
Keywords: open_source github
Platform: UNKNOWN
Classifier: Topic :: Software Development :: Version Control :: Git
Classifier: Topic :: System :: Software Distribution
Classifier: Development Status :: 5 - Production/Stable
Classifier: Intended Audience :: Developers
Classifier: Intended Audience :: Science/Research
Classifier: Programming Language :: Python :: 3 :: Only
Classifier: Operating System :: OS Independent
Requires-Python: >=3.6
Requires-Dist: beautifulsoup4 (==4.10.0)
Requires-Dist: folium (==0.12.1)
Requires-Dist: pandas (==1.3.4)
Requires-Dist: pytest (==6.2.5)
Requires-Dist: requests (==2.26.0)
